AUTHORS.rst
HISTORY.rst
MANIFEST.in
README.txt
setup.py
examples/Allnews.py
examples/Politicsnews.py
examples/__init__.py
teheran_news/__init__.py
teheran_news/article.py
teheran_news/objectview.py
teheran_news/teheran_news.py
teheran_news/utilities.py
teheran_news.egg-info/PKG-INFO
teheran_news.egg-info/SOURCES.txt
teheran_news.egg-info/dependency_links.txt
teheran_news.egg-info/requires.txt
teheran_news.egg-info/top_level.txt
test/__init__.py
test/test_teheran_news.py