Metadata-Version: 2.1
Name: teheran-news
Version: 0.0.1
Summary: A web scrapping tool for teherannews.com
Home-page: https://github.com/cesardeaptude/teheran_news
Author: César Pérez Moreno
Author-email: cperez@aptude.com
License: MIT
Platform: UNKNOWN
Requires-Python: >=3
